ipregion/__init__.py
ipregion/db.py
ipregion/ip2region.xdb
ipregion/ipcache.sample.db3
ipregion/xdbSearcher.py
ip_region-1.0.6.dist-info/LICENSE
ip_region-1.0.6.dist-info/METADATA
ip_region-1.0.6.dist-info/WHEEL
ip_region-1.0.6.dist-info/top_level.txt
ip_region-1.0.6.dist-info/RECORD
