Metadata-Version: 2.1
Name: ip-region
Version: 1.0.6
Summary: Get geographic location through IP address, support IPv4 and IPv6. Combine IP address library and online API.
Home-page: https://github.com/jeeaay/py-ip-location
Author: Jeay
Author-email: admin@jeay.net
License: Apache-2.0 License
Keywords: ip loaction,ip country,ip region,IP address loaction,IP geographic location
Platform: any
License-File: LICENSE
Requires-Dist: requests
